{"fonts/NotoSansJP-Black.otf":["fonts/NotoSansJP-Black.otf"],"fonts/NotoSansJP-Bold.otf":["fonts/NotoSansJP-Bold.otf"],"fonts/NotoSansJP-Light.otf":["fonts/NotoSansJP-Light.otf"],"fonts/NotoSansJP-Medium.otf":["fonts/NotoSansJP-Medium.otf"],"fonts/NotoSansJP-Regular.otf":["fonts/NotoSansJP-Regular.otf"],"fonts/NotoSansJP-Thin.otf":["fonts/NotoSansJP-Thin.otf"],"odai_list.txt":["odai_list.txt"],"packages/cupertino_icons/assets/CupertinoIcons.ttf":["packages/cupertino_icons/assets/CupertinoIcons.ttf"]}